authlib_gino/__init__.py
authlib_gino/async_grants/__init__.py
authlib_gino/async_grants/authorization_code.py
authlib_gino/async_grants/base.py
authlib_gino/async_grants/oidc_code.py
authlib_gino/async_grants/refresh_token.py
authlib_gino/fastapi_session/__init__.py
authlib_gino/fastapi_session/admin.py
authlib_gino/fastapi_session/api.py
authlib_gino/fastapi_session/config.py
authlib_gino/fastapi_session/demo_login.py
authlib_gino/fastapi_session/gino_app.py
authlib_gino/fastapi_session/impl.py
authlib_gino/fastapi_session/migrations/README
authlib_gino/fastapi_session/migrations/env.py
authlib_gino/fastapi_session/migrations/script.py.mako
authlib_gino/fastapi_session/migrations/versions/6a8703b98396_token_identity.py
authlib_gino/fastapi_session/migrations/versions/a36c9db3f264_initial.py
authlib_gino/fastapi_session/models.py
authlib_gino/fastapi_session/oidc.py
authlib_gino/gino_oauth2/__init__.py
authlib_gino/gino_oauth2/client_mixin.py
authlib_gino/gino_oauth2/functions.py
authlib_gino/gino_oauth2/tokens_mixins.py
authlib_gino/starlette_oauth2/__init__.py
authlib_gino/starlette_oauth2/async_authenticate_client.py
authlib_gino/starlette_oauth2/authorization_server.py
authlib_gino-0.3.0.dist-info/entry_points.txt
authlib_gino-0.3.0.dist-info/WHEEL
authlib_gino-0.3.0.dist-info/METADATA
authlib_gino-0.3.0.dist-info/RECORD
